setup.py
test/__init__.py
test/test_acceptance.py
travis_bump_version.egg-info/PKG-INFO
travis_bump_version.egg-info/SOURCES.txt
travis_bump_version.egg-info/dependency_links.txt
travis_bump_version.egg-info/entry_points.txt
travis_bump_version.egg-info/requires.txt
travis_bump_version.egg-info/top_level.txt
travis_bump_version.egg-info/zip-safe
travisbumpversion/__init__.py
travisbumpversion/main.py