Metadata-Version: 1.1
Name: travis-bump-version
Version: 0.1.12
Summary: Bump version files on travis builds
Home-page: http://github.com/polysquare/travis-runner
Author: Sam Spilsbury
Author-email: smspillaz@gmail.com
License: MIT
Keywords: development linters
Platform: UNKNOWN
Classifier: Development Status :: 3 - Alpha
Classifier: Programming Language :: Python :: 2
Classifier: Programming Language :: Python :: 2.7
Classifier: Programming Language :: Python :: 3
Classifier: Programming Language :: Python :: 3.1
Classifier: Programming Language :: Python :: 3.2
Classifier: Programming Language :: Python :: 3.3
Classifier: Programming Language :: Python :: 3.4
Classifier: Intended Audience :: Developers
Classifier: Topic :: Software Development :: Build Tools
Classifier: License :: OSI Approved :: MIT License
